{
  "data": {
    "title": "அறுபத்தி நான்கு கலைகள்",
    "soothiram": "",
    "desc": "",
    "example": "எழுத்திலக்கணம், எழுத்தாற்றல், கணிதவியல், மறை நூல், தொன்மம்",
    "type": [
      {
        "title": "அறுபத்தி நான்கு கலைகள்",
        "soothiram": "",
        "desc": "",
        "example": "",
        "type": [
          {
            "title": "எழுத்திலக்கணம்",
            "soothiram": "அகரம் முதல் னகர இறுவாய் முப்பஃது என்ப - தொல்காப்பியம் \n உயிரும் உடம்புமாம் முப்பது முதலே - நன்னூல் \n அம்முதல் ஈறாறு ஆவி கம்முதல்\n மெய்ம்மூ ஆறென விளம்பினர் புலவர் - நன்னூல்",
            "desc": "உயிரெழுத்துக்கள் பன்னிரெண்டும் மெய்யெழுத்துக்கள் பதிணெட்டும் ஆகிய முப்பது எழுத்துக்களும் முதலெழுத்துக்கள் என கூறப்படுகிறது.",
            "example": "அ, ஆ, இ, ஈ, உ, ஊ, எ, ஏ, ஐ, ஒ, ஓ, ஔ, - உயிரெழுத்துக்கள் \n க், ங், ச், ஞ், ட், ண், த், ந், ப், ம், ய், ர், ல், வ், ழ், ள், ற்,ன் - மெய்யெழுத்துக்கள்",
            "type": []
          },
          {
            "title": "எழுத்தாற்றல்",
            "soothiram": "",
            "desc": "சார்ந்து வரல் மரபின் மூன்று அலங்கடையே.\n அவைதாம், \nகுற்றியலிகரம் குற்றியலுகரம் \nஆய்தம் என்ற \nமுப்பாற்புள்ளியும் எழுத்து ஓரன்ன. \n உயிர்மெய் ஆய்தம் உயிரளபு ஒற்றளபு \nஅஃகிய இ உ ஐ ஓள மஃகான்\nதனிநிலை பத்துஞ் சார்பெழுத் தாகும்",
            "example": "",
            "type": []
          },
          {
            "title": "கணிதவியல்",
            "soothiram": "அ இ உ அம் மூன்றும் சுட்டு \n - தொல்காப்பியம் \n ",
            "desc": "",
            "example": "",
            "type": [

            ]
          },
          {
            "title": "மறை நூல்",
            "soothiram": "ஆ ஏ ஓ அம் மூன்றும் வினா \n - தொல்காப்பியம் \n ",
            "desc": "",
            "example": "",
            "type": [

            ]
          },
          {
            "title": "தொன்மம்",
            "soothiram": "",
            "desc": "",
            "example": "",
            "type": [

            ]
          }
        ]
      },
      {
        "title": "மற்ற கலைகள்",
        "soothiram": "",
        "desc": "",
        "example": "",
        "type": [

        ]
      },
      {
        "title": "கடபயாதி",
        "soothiram": "",
        "desc": "",
        "example": "",
        "type": [
          {
            "title": "carnatic music",
            "soothiram": "அகரம் முதல் னகர இறுவாய் முப்பஃது என்ப - தொல்காப்பியம் \n உயிரும் உடம்புமாம் முப்பது முதலே - நன்னூல் \n அம்முதல் ஈறாறு ஆவி கம்முதல்\n மெய்ம்மூ ஆறென விளம்பினர் புலவர் - நன்னூல்",
            "desc": "உயிரெழுத்துக்கள் பன்னிரெண்டும் மெய்யெழுத்துக்கள் பதிணெட்டும் ஆகிய முப்பது எழுத்துக்களும் முதலெழுத்துக்கள் என கூறப்படுகிறது.",
            "example": "அ, ஆ, இ, ஈ, உ, ஊ, எ, ஏ, ஐ, ஒ, ஓ, ஔ, - உயிரெழுத்துக்கள் \n க், ங், ச், ஞ், ட், ண், த், ந், ப், ம், ய், ர், ல், வ், ழ், ள், ற்,ன் - மெய்யெழுத்துக்கள்",
            "type": []
          },
          {
            "title": "other poems with encryption",
            "soothiram": "அகரம் முதல் னகர இறுவாய் முப்பஃது என்ப - தொல்காப்பியம் \n உயிரும் உடம்புமாம் முப்பது முதலே - நன்னூல் \n அம்முதல் ஈறாறு ஆவி கம்முதல்\n மெய்ம்மூ ஆறென விளம்பினர் புலவர் - நன்னூல்",
            "desc": "உயிரெழுத்துக்கள் பன்னிரெண்டும் மெய்யெழுத்துக்கள் பதிணெட்டும் ஆகிய முப்பது எழுத்துக்களும் முதலெழுத்துக்கள் என கூறப்படுகிறது.",
            "example": "அ, ஆ, இ, ஈ, உ, ஊ, எ, ஏ, ஐ, ஒ, ஓ, ஔ, - உயிரெழுத்துக்கள் \n க், ங், ச், ஞ், ட், ண், த், ந், ப், ம், ய், ர், ல், வ், ழ், ள், ற்,ன் - மெய்யெழுத்துக்கள்",
            "type": []
          }
        ]
      },
      {
        "title": "அவதானம்",
        "soothiram": "",
        "desc": "",
        "example": "",
        "type": [
          {
            "title": "dhasavadhani",
            "soothiram": "அகரம் முதல் னகர இறுவாய் முப்பஃது என்ப - தொல்காப்பியம் \n உயிரும் உடம்புமாம் முப்பது முதலே - நன்னூல் \n அம்முதல் ஈறாறு ஆவி கம்முதல்\n மெய்ம்மூ ஆறென விளம்பினர் புலவர் - நன்னூல்",
            "desc": "உயிரெழுத்துக்கள் பன்னிரெண்டும் மெய்யெழுத்துக்கள் பதிணெட்டும் ஆகிய முப்பது எழுத்துக்களும் முதலெழுத்துக்கள் என கூறப்படுகிறது.",
            "example": "அ, ஆ, இ, ஈ, உ, ஊ, எ, ஏ, ஐ, ஒ, ஓ, ஔ, - உயிரெழுத்துக்கள் \n க், ங், ச், ஞ், ட், ண், த், ந், ப், ம், ய், ர், ல், வ், ழ், ள், ற்,ன் - மெய்யெழுத்துக்கள்",
            "type": []
          },
          {
            "title": "sathavadhani",
            "soothiram": "அகரம் முதல் னகர இறுவாய் முப்பஃது என்ப - தொல்காப்பியம் \n உயிரும் உடம்புமாம் முப்பது முதலே - நன்னூல் \n அம்முதல் ஈறாறு ஆவி கம்முதல்\n மெய்ம்மூ ஆறென விளம்பினர் புலவர் - நன்னூல்",
            "desc": "உயிரெழுத்துக்கள் பன்னிரெண்டும் மெய்யெழுத்துக்கள் பதிணெட்டும் ஆகிய முப்பது எழுத்துக்களும் முதலெழுத்துக்கள் என கூறப்படுகிறது.",
            "example": "அ, ஆ, இ, ஈ, உ, ஊ, எ, ஏ, ஐ, ஒ, ஓ, ஔ, - உயிரெழுத்துக்கள் \n க், ங், ச், ஞ், ட், ண், த், ந், ப், ம், ய், ர், ல், வ், ழ், ள், ற்,ன் - மெய்யெழுத்துக்கள்",
            "type": []
          },
          {
            "title": "sahasravadhani",
            "soothiram": "அகரம் முதல் னகர இறுவாய் முப்பஃது என்ப - தொல்காப்பியம் \n உயிரும் உடம்புமாம் முப்பது முதலே - நன்னூல் \n அம்முதல் ஈறாறு ஆவி கம்முதல்\n மெய்ம்மூ ஆறென விளம்பினர் புலவர் - நன்னூல்",
            "desc": "உயிரெழுத்துக்கள் பன்னிரெண்டும் மெய்யெழுத்துக்கள் பதிணெட்டும் ஆகிய முப்பது எழுத்துக்களும் முதலெழுத்துக்கள் என கூறப்படுகிறது.",
            "example": "அ, ஆ, இ, ஈ, உ, ஊ, எ, ஏ, ஐ, ஒ, ஓ, ஔ, - உயிரெழுத்துக்கள் \n க், ங், ச், ஞ், ட், ண், த், ந், ப், ம், ய், ர், ல், வ், ழ், ள், ற்,ன் - மெய்யெழுத்துக்கள்",
            "type": []
          }
        ]
      },
      {
        "title": "அறம் வைத்து பாடுதல்",
        "soothiram": "",
        "desc": "",
        "example": "",
        "type": [
          {
            "title": "nandi kalambagam",
            "soothiram": "அகரம் முதல் னகர இறுவாய் முப்பஃது என்ப - தொல்காப்பியம் \n உயிரும் உடம்புமாம் முப்பது முதலே - நன்னூல் \n அம்முதல் ஈறாறு ஆவி கம்முதல்\n மெய்ம்மூ ஆறென விளம்பினர் புலவர் - நன்னூல்",
            "desc": "உயிரெழுத்துக்கள் பன்னிரெண்டும் மெய்யெழுத்துக்கள் பதிணெட்டும் ஆகிய முப்பது எழுத்துக்களும் முதலெழுத்துக்கள் என கூறப்படுகிறது.",
            "example": "அ, ஆ, இ, ஈ, உ, ஊ, எ, ஏ, ஐ, ஒ, ஓ, ஔ, - உயிரெழுத்துக்கள் \n க், ங், ச், ஞ், ட், ண், த், ந், ப், ம், ய், ர், ல், வ், ழ், ள், ற்,ன் - மெய்யெழுத்துக்கள்",
            "type": []
          },
          {
            "title": "kalamega pulavar(emagandam)",
            "soothiram": "அகரம் முதல் னகர இறுவாய் முப்பஃது என்ப - தொல்காப்பியம் \n உயிரும் உடம்புமாம் முப்பது முதலே - நன்னூல் \n அம்முதல் ஈறாறு ஆவி கம்முதல்\n மெய்ம்மூ ஆறென விளம்பினர் புலவர் - நன்னூல்",
            "desc": "உயிரெழுத்துக்கள் பன்னிரெண்டும் மெய்யெழுத்துக்கள் பதிணெட்டும் ஆகிய முப்பது எழுத்துக்களும் முதலெழுத்துக்கள் என கூறப்படுகிறது.",
            "example": "அ, ஆ, இ, ஈ, உ, ஊ, எ, ஏ, ஐ, ஒ, ஓ, ஔ, - உயிரெழுத்துக்கள் \n க், ங், ச், ஞ், ட், ண், த், ந், ப், ம், ய், ர், ல், வ், ழ், ள், ற்,ன் - மெய்யெழுத்துக்கள்",
            "type": []
          },
          {
            "title": "kalamega pulavar(paakadikum siruvargal naaku, other poems)",
            "soothiram": "அகரம் முதல் னகர இறுவாய் முப்பஃது என்ப - தொல்காப்பியம் \n உயிரும் உடம்புமாம் முப்பது முதலே - நன்னூல் \n அம்முதல் ஈறாறு ஆவி கம்முதல்\n மெய்ம்மூ ஆறென விளம்பினர் புலவர் - நன்னூல்",
            "desc": "உயிரெழுத்துக்கள் பன்னிரெண்டும் மெய்யெழுத்துக்கள் பதிணெட்டும் ஆகிய முப்பது எழுத்துக்களும் முதலெழுத்துக்கள் என கூறப்படுகிறது.",
            "example": "அ, ஆ, இ, ஈ, உ, ஊ, எ, ஏ, ஐ, ஒ, ஓ, ஔ, - உயிரெழுத்துக்கள் \n க், ங், ச், ஞ், ட், ண், த், ந், ப், ம், ய், ர், ல், வ், ழ், ள், ற்,ன் - மெய்யெழுத்துக்கள்",
            "type": []
          },
          {
            "title": "kannadasan",
            "soothiram": "அகரம் முதல் னகர இறுவாய் முப்பஃது என்ப - தொல்காப்பியம் \n உயிரும் உடம்புமாம் முப்பது முதலே - நன்னூல் \n அம்முதல் ஈறாறு ஆவி கம்முதல்\n மெய்ம்மூ ஆறென விளம்பினர் புலவர் - நன்னூல்",
            "desc": "உயிரெழுத்துக்கள் பன்னிரெண்டும் மெய்யெழுத்துக்கள் பதிணெட்டும் ஆகிய முப்பது எழுத்துக்களும் முதலெழுத்துக்கள் என கூறப்படுகிறது.",
            "example": "அ, ஆ, இ, ஈ, உ, ஊ, எ, ஏ, ஐ, ஒ, ஓ, ஔ, - உயிரெழுத்துக்கள் \n க், ங், ச், ஞ், ட், ண், த், ந், ப், ம், ய், ர், ல், வ், ழ், ள், ற்,ன் - மெய்யெழுத்துக்கள்",
            "type": []
          },
          {
            "title": "mahakavi bharathiyar",
            "soothiram": "அகரம் முதல் னகர இறுவாய் முப்பஃது என்ப - தொல்காப்பியம் \n உயிரும் உடம்புமாம் முப்பது முதலே - நன்னூல் \n அம்முதல் ஈறாறு ஆவி கம்முதல்\n மெய்ம்மூ ஆறென விளம்பினர் புலவர் - நன்னூல்",
            "desc": "உயிரெழுத்துக்கள் பன்னிரெண்டும் மெய்யெழுத்துக்கள் பதிணெட்டும் ஆகிய முப்பது எழுத்துக்களும் முதலெழுத்துக்கள் என கூறப்படுகிறது.",
            "example": "அ, ஆ, இ, ஈ, உ, ஊ, எ, ஏ, ஐ, ஒ, ஓ, ஔ, - உயிரெழுத்துக்கள் \n க், ங், ச், ஞ், ட், ண், த், ந், ப், ம், ய், ர், ல், வ், ழ், ள், ற்,ன் - மெய்யெழுத்துக்கள்",
            "type": []
          }
        ]
      },
      {
        "title": "தமிழ் கவிப்புலமை",
        "soothiram": "",
        "desc": "",
        "example": "",
        "type": [
          {
            "title": "avvaiyarum, kambarum kabilarum ottakootharum(aarai keerai)",
            "soothiram": "அகரம் முதல் னகர இறுவாய் முப்பஃது என்ப - தொல்காப்பியம் \n உயிரும் உடம்புமாம் முப்பது முதலே - நன்னூல் \n அம்முதல் ஈறாறு ஆவி கம்முதல்\n மெய்ம்மூ ஆறென விளம்பினர் புலவர் - நன்னூல்",
            "desc": "உயிரெழுத்துக்கள் பன்னிரெண்டும் மெய்யெழுத்துக்கள் பதிணெட்டும் ஆகிய முப்பது எழுத்துக்களும் முதலெழுத்துக்கள் என கூறப்படுகிறது.",
            "example": "அ, ஆ, இ, ஈ, உ, ஊ, எ, ஏ, ஐ, ஒ, ஓ, ஔ, - உயிரெழுத்துக்கள் \n க், ங், ச், ஞ், ட், ண், த், ந், ப், ம், ய், ர், ல், வ், ழ், ள், ற்,ன் - மெய்யெழுத்துக்கள்",
            "type": []
          },
          {
            "title": "mukkalalil moovirandu pogayile",
            "soothiram": "அகரம் முதல் னகர இறுவாய் முப்பஃது என்ப - தொல்காப்பியம் \n உயிரும் உடம்புமாம் முப்பது முதலே - நன்னூல் \n அம்முதல் ஈறாறு ஆவி கம்முதல்\n மெய்ம்மூ ஆறென விளம்பினர் புலவர் - நன்னூல்",
            "desc": "உயிரெழுத்துக்கள் பன்னிரெண்டும் மெய்யெழுத்துக்கள் பதிணெட்டும் ஆகிய முப்பது எழுத்துக்களும் முதலெழுத்துக்கள் என கூறப்படுகிறது.",
            "example": "அ, ஆ, இ, ஈ, உ, ஊ, எ, ஏ, ஐ, ஒ, ஓ, ஔ, - உயிரெழுத்துக்கள் \n க், ங், ச், ஞ், ட், ண், த், ந், ப், ம், ய், ர், ல், வ், ழ், ள், ற்,ன் - மெய்யெழுத்துக்கள்",
            "type": []
          },
          {
            "title": "kambarum pulavarum(mannuni maapilaye)",
            "soothiram": "அகரம் முதல் னகர இறுவாய் முப்பஃது என்ப - தொல்காப்பியம் \n உயிரும் உடம்புமாம் முப்பது முதலே - நன்னூல் \n அம்முதல் ஈறாறு ஆவி கம்முதல்\n மெய்ம்மூ ஆறென விளம்பினர் புலவர் - நன்னூல்",
            "desc": "உயிரெழுத்துக்கள் பன்னிரெண்டும் மெய்யெழுத்துக்கள் பதிணெட்டும் ஆகிய முப்பது எழுத்துக்களும் முதலெழுத்துக்கள் என கூறப்படுகிறது.",
            "example": "அ, ஆ, இ, ஈ, உ, ஊ, எ, ஏ, ஐ, ஒ, ஓ, ஔ, - உயிரெழுத்துக்கள் \n க், ங், ச், ஞ், ட், ண், த், ந், ப், ம், ய், ர், ல், வ், ழ், ள், ற்,ன் - மெய்யெழுத்துக்கள்",
            "type": []
          },
          {
            "title": "kalamega pulavar",
            "soothiram": "அகரம் முதல் னகர இறுவாய் முப்பஃது என்ப - தொல்காப்பியம் \n உயிரும் உடம்புமாம் முப்பது முதலே - நன்னூல் \n அம்முதல் ஈறாறு ஆவி கம்முதல்\n மெய்ம்மூ ஆறென விளம்பினர் புலவர் - நன்னூல்",
            "desc": "உயிரெழுத்துக்கள் பன்னிரெண்டும் மெய்யெழுத்துக்கள் பதிணெட்டும் ஆகிய முப்பது எழுத்துக்களும் முதலெழுத்துக்கள் என கூறப்படுகிறது.",
            "example": "அ, ஆ, இ, ஈ, உ, ஊ, எ, ஏ, ஐ, ஒ, ஓ, ஔ, - உயிரெழுத்துக்கள் \n க், ங், ச், ஞ், ட், ண், த், ந், ப், ம், ய், ர், ல், வ், ழ், ள், ற்,ன் - மெய்யெழுத்துக்கள்",
            "type": []
          },
          {
            "title": "padikasu pulavar(paalum kasakavilai thuniyum kasakavilai)",
            "soothiram": "அகரம் முதல் னகர இறுவாய் முப்பஃது என்ப - தொல்காப்பியம் \n உயிரும் உடம்புமாம் முப்பது முதலே - நன்னூல் \n அம்முதல் ஈறாறு ஆவி கம்முதல்\n மெய்ம்மூ ஆறென விளம்பினர் புலவர் - நன்னூல்",
            "desc": "உயிரெழுத்துக்கள் பன்னிரெண்டும் மெய்யெழுத்துக்கள் பதிணெட்டும் ஆகிய முப்பது எழுத்துக்களும் முதலெழுத்துக்கள் என கூறப்படுகிறது.",
            "example": "அ, ஆ, இ, ஈ, உ, ஊ, எ, ஏ, ஐ, ஒ, ஓ, ஔ, - உயிரெழுத்துக்கள் \n க், ங், ச், ஞ், ட், ண், த், ந், ப், ம், ய், ர், ல், வ், ழ், ள், ற்,ன் - மெய்யெழுத்துக்கள்",
            "type": []
          },
          {
            "title": "iratai pulavargal",
            "soothiram": "அகரம் முதல் னகர இறுவாய் முப்பஃது என்ப - தொல்காப்பியம் \n உயிரும் உடம்புமாம் முப்பது முதலே - நன்னூல் \n அம்முதல் ஈறாறு ஆவி கம்முதல்\n மெய்ம்மூ ஆறென விளம்பினர் புலவர் - நன்னூல்",
            "desc": "உயிரெழுத்துக்கள் பன்னிரெண்டும் மெய்யெழுத்துக்கள் பதிணெட்டும் ஆகிய முப்பது எழுத்துக்களும் முதலெழுத்துக்கள் என கூறப்படுகிறது.",
            "example": "அ, ஆ, இ, ஈ, உ, ஊ, எ, ஏ, ஐ, ஒ, ஓ, ஔ, - உயிரெழுத்துக்கள் \n க், ங், ச், ஞ், ட், ண், த், ந், ப், ம், ய், ர், ல், வ், ழ், ள், ற்,ன் - மெய்யெழுத்துக்கள்",
            "type": []
          },
          {
            "title": "paarkadalil seenivasan palikondirukiran",
            "soothiram": "அகரம் முதல் னகர இறுவாய் முப்பஃது என்ப - தொல்காப்பியம் \n உயிரும் உடம்புமாம் முப்பது முதலே - நன்னூல் \n அம்முதல் ஈறாறு ஆவி கம்முதல்\n மெய்ம்மூ ஆறென விளம்பினர் புலவர் - நன்னூல்",
            "desc": "உயிரெழுத்துக்கள் பன்னிரெண்டும் மெய்யெழுத்துக்கள் பதிணெட்டும் ஆகிய முப்பது எழுத்துக்களும் முதலெழுத்துக்கள் என கூறப்படுகிறது.",
            "example": "அ, ஆ, இ, ஈ, உ, ஊ, எ, ஏ, ஐ, ஒ, ஓ, ஔ, - உயிரெழுத்துக்கள் \n க், ங், ச், ஞ், ட், ண், த், ந், ப், ம், ய், ர், ல், வ், ழ், ள், ற்,ன் - மெய்யெழுத்துக்கள்",
            "type": []
          },
          {
            "title": "ottakoothar paatirku irratai thazpal",
            "soothiram": "அகரம் முதல் னகர இறுவாய் முப்பஃது என்ப - தொல்காப்பியம் \n உயிரும் உடம்புமாம் முப்பது முதலே - நன்னூல் \n அம்முதல் ஈறாறு ஆவி கம்முதல்\n மெய்ம்மூ ஆறென விளம்பினர் புலவர் - நன்னூல்",
            "desc": "உயிரெழுத்துக்கள் பன்னிரெண்டும் மெய்யெழுத்துக்கள் பதிணெட்டும் ஆகிய முப்பது எழுத்துக்களும் முதலெழுத்துக்கள் என கூறப்படுகிறது.",
            "example": "அ, ஆ, இ, ஈ, உ, ஊ, எ, ஏ, ஐ, ஒ, ஓ, ஔ, - உயிரெழுத்துக்கள் \n க், ங், ச், ஞ், ட், ண், த், ந், ப், ம், ய், ர், ல், வ், ழ், ள், ற்,ன் - மெய்யெழுத்துக்கள்",
            "type": []
          },
          {
            "title": "abirami battar",
            "soothiram": "அகரம் முதல் னகர இறுவாய் முப்பஃது என்ப - தொல்காப்பியம் \n உயிரும் உடம்புமாம் முப்பது முதலே - நன்னூல் \n அம்முதல் ஈறாறு ஆவி கம்முதல்\n மெய்ம்மூ ஆறென விளம்பினர் புலவர் - நன்னூல்",
            "desc": "உயிரெழுத்துக்கள் பன்னிரெண்டும் மெய்யெழுத்துக்கள் பதிணெட்டும் ஆகிய முப்பது எழுத்துக்களும் முதலெழுத்துக்கள் என கூறப்படுகிறது.",
            "example": "அ, ஆ, இ, ஈ, உ, ஊ, எ, ஏ, ஐ, ஒ, ஓ, ஔ, - உயிரெழுத்துக்கள் \n க், ங், ச், ஞ், ட், ண், த், ந், ப், ம், ய், ர், ல், வ், ழ், ள், ற்,ன் - மெய்யெழுத்துக்கள்",
            "type": []
          },
          {
            "title": "andhahakavi veeraraghava mudaliyar(இம்பர் வான் எல்லை இராமனையே பாடி)",
            "soothiram": "அகரம் முதல் னகர இறுவாய் முப்பஃது என்ப - தொல்காப்பியம் \n உயிரும் உடம்புமாம் முப்பது முதலே - நன்னூல் \n அம்முதல் ஈறாறு ஆவி கம்முதல்\n மெய்ம்மூ ஆறென விளம்பினர் புலவர் - நன்னூல்",
            "desc": "உயிரெழுத்துக்கள் பன்னிரெண்டும் மெய்யெழுத்துக்கள் பதிணெட்டும் ஆகிய முப்பது எழுத்துக்களும் முதலெழுத்துக்கள் என கூறப்படுகிறது.",
            "example": "அ, ஆ, இ, ஈ, உ, ஊ, எ, ஏ, ஐ, ஒ, ஓ, ஔ, - உயிரெழுத்துக்கள் \n க், ங், ச், ஞ், ட், ண், த், ந், ப், ம், ய், ர், ல், வ், ழ், ள், ற்,ன் - மெய்யெழுத்துக்கள்",
            "type": []
          },
          {
            "title": "poyya mozhi pulavar",
            "soothiram": "அகரம் முதல் னகர இறுவாய் முப்பஃது என்ப - தொல்காப்பியம் \n உயிரும் உடம்புமாம் முப்பது முதலே - நன்னூல் \n அம்முதல் ஈறாறு ஆவி கம்முதல்\n மெய்ம்மூ ஆறென விளம்பினர் புலவர் - நன்னூல்",
            "desc": "உயிரெழுத்துக்கள் பன்னிரெண்டும் மெய்யெழுத்துக்கள் பதிணெட்டும் ஆகிய முப்பது எழுத்துக்களும் முதலெழுத்துக்கள் என கூறப்படுகிறது.",
            "example": "அ, ஆ, இ, ஈ, உ, ஊ, எ, ஏ, ஐ, ஒ, ஓ, ஔ, - உயிரெழுத்துக்கள் \n க், ங், ச், ஞ், ட், ண், த், ந், ப், ம், ய், ர், ல், வ், ழ், ள், ற்,ன் - மெய்யெழுத்துக்கள்",
            "type": []
          },
          {
            "title": "oppilla mani pulavar",
            "soothiram": "அகரம் முதல் னகர இறுவாய் முப்பஃது என்ப - தொல்காப்பியம் \n உயிரும் உடம்புமாம் முப்பது முதலே - நன்னூல் \n அம்முதல் ஈறாறு ஆவி கம்முதல்\n மெய்ம்மூ ஆறென விளம்பினர் புலவர் - நன்னூல்",
            "desc": "உயிரெழுத்துக்கள் பன்னிரெண்டும் மெய்யெழுத்துக்கள் பதிணெட்டும் ஆகிய முப்பது எழுத்துக்களும் முதலெழுத்துக்கள் என கூறப்படுகிறது.",
            "example": "அ, ஆ, இ, ஈ, உ, ஊ, எ, ஏ, ஐ, ஒ, ஓ, ஔ, - உயிரெழுத்துக்கள் \n க், ங், ச், ஞ், ட், ண், த், ந், ப், ம், ய், ர், ல், வ், ழ், ள், ற்,ன் - மெய்யெழுத்துக்கள்",
            "type": []
          },
          {
            "title": "palapattadai sokkanadha pulavar",
            "soothiram": "அகரம் முதல் னகர இறுவாய் முப்பஃது என்ப - தொல்காப்பியம் \n உயிரும் உடம்புமாம் முப்பது முதலே - நன்னூல் \n அம்முதல் ஈறாறு ஆவி கம்முதல்\n மெய்ம்மூ ஆறென விளம்பினர் புலவர் - நன்னூல்",
            "desc": "உயிரெழுத்துக்கள் பன்னிரெண்டும் மெய்யெழுத்துக்கள் பதிணெட்டும் ஆகிய முப்பது எழுத்துக்களும் முதலெழுத்துக்கள் என கூறப்படுகிறது.",
            "example": "அ, ஆ, இ, ஈ, உ, ஊ, எ, ஏ, ஐ, ஒ, ஓ, ஔ, - உயிரெழுத்துக்கள் \n க், ங், ச், ஞ், ட், ண், த், ந், ப், ம், ய், ர், ல், வ், ழ், ள், ற்,ன் - மெய்யெழுத்துக்கள்",
            "type": []
          },
          {
            "title": "adhiveera rama pandian",
            "soothiram": "அகரம் முதல் னகர இறுவாய் முப்பஃது என்ப - தொல்காப்பியம் \n உயிரும் உடம்புமாம் முப்பது முதலே - நன்னூல் \n அம்முதல் ஈறாறு ஆவி கம்முதல்\n மெய்ம்மூ ஆறென விளம்பினர் புலவர் - நன்னூல்",
            "desc": "உயிரெழுத்துக்கள் பன்னிரெண்டும் மெய்யெழுத்துக்கள் பதிணெட்டும் ஆகிய முப்பது எழுத்துக்களும் முதலெழுத்துக்கள் என கூறப்படுகிறது.",
            "example": "அ, ஆ, இ, ஈ, உ, ஊ, எ, ஏ, ஐ, ஒ, ஓ, ஔ, - உயிரெழுத்துக்கள் \n க், ங், ச், ஞ், ட், ண், த், ந், ப், ம், ய், ர், ல், வ், ழ், ள், ற்,ன் - மெய்யெழுத்துக்கள்",
            "type": []
          },
          {
            "title": "arunagiri nadhar",
            "soothiram": "அகரம் முதல் னகர இறுவாய் முப்பஃது என்ப - தொல்காப்பியம் \n உயிரும் உடம்புமாம் முப்பது முதலே - நன்னூல் \n அம்முதல் ஈறாறு ஆவி கம்முதல்\n மெய்ம்மூ ஆறென விளம்பினர் புலவர் - நன்னூல்",
            "desc": "உயிரெழுத்துக்கள் பன்னிரெண்டும் மெய்யெழுத்துக்கள் பதிணெட்டும் ஆகிய முப்பது எழுத்துக்களும் முதலெழுத்துக்கள் என கூறப்படுகிறது.",
            "example": "அ, ஆ, இ, ஈ, உ, ஊ, எ, ஏ, ஐ, ஒ, ஓ, ஔ, - உயிரெழுத்துக்கள் \n க், ங், ச், ஞ், ட், ண், த், ந், ப், ம், ய், ர், ல், வ், ழ், ள், ற்,ன் - மெய்யெழுத்துக்கள்",
            "type": []
          },
          {
            "title": "ekaambavaanar",
            "soothiram": "அகரம் முதல் னகர இறுவாய் முப்பஃது என்ப - தொல்காப்பியம் \n உயிரும் உடம்புமாம் முப்பது முதலே - நன்னூல் \n அம்முதல் ஈறாறு ஆவி கம்முதல்\n மெய்ம்மூ ஆறென விளம்பினர் புலவர் - நன்னூல்",
            "desc": "உயிரெழுத்துக்கள் பன்னிரெண்டும் மெய்யெழுத்துக்கள் பதிணெட்டும் ஆகிய முப்பது எழுத்துக்களும் முதலெழுத்துக்கள் என கூறப்படுகிறது.",
            "example": "அ, ஆ, இ, ஈ, உ, ஊ, எ, ஏ, ஐ, ஒ, ஓ, ஔ, - உயிரெழுத்துக்கள் \n க், ங், ச், ஞ், ட், ண், த், ந், ப், ம், ய், ர், ல், வ், ழ், ள், ற்,ன் - மெய்யெழுத்துக்கள்",
            "type": []
          }
        ]
      }
    ]
  }
}